{
  "orphanPages": [
    {
      "file": "frontend\\src\\pages\\admin\\Communications.tsx",
      "reason": "Not included in routing configuration",
      "action": "Remove or integrate into complaints-and-feedback if broader scope"
    },
    {
      "file": "frontend\\src\\pages\\admin\\CookApprovals.tsx",
      "reason": "Not included in routing configuration",
      "action": "Remove or integrate into user-management"
    },
    {
      "file": "frontend\\src\\pages\\admin\\DeliveryAgentApprovals.tsx",
      "reason": "Not included in routing configuration",
      "action": "Remove or integrate into user-management"
    },
    {
      "file": "frontend\\src\\pages\\admin\\Profile.tsx",
      "reason": "Not included in routing configuration",
      "action": "Remove or integrate into settings"
    },
    {
      "file": "frontend\\src\\pages\\admin\\Reports.tsx",
      "reason": "Not included in routing configuration",
      "action": "Remove or integrate into system-analytics"
    },
    {
      "file": "frontend\\src\\pages\\admin\\UnifiedApprovals.tsx",
      "reason": "Not included in routing configuration",
      "action": "Remove or merge into user-management"
    },
    {
      "file": "frontend\\src\\pages\\admin\\UserApproval.tsx",
      "reason": "Not included in routing configuration",
      "action": "Remove or integrate into user-management"
    },
    {
      "file": "frontend\\src\\pages\\admin\\communications\\ComplaintManagement.tsx",
      "reason": "Re-export page, not directly routed",
      "action": "Remove, use component directly if needed"
    },
    {
      "file": "frontend\\src\\pages\\admin\\communications\\EmailTemplates.tsx",
      "reason": "Re-export page, not directly routed",
      "action": "Remove, use component directly if needed"
    },
    {
      "file": "frontend\\src\\pages\\admin\\communications\\FeedbackManagement.tsx",
      "reason": "Re-export page, not directly routed",
      "action": "Remove, use component directly if needed"
    },
    {
      "file": "frontend\\src\\pages\\admin\\communications\\SystemAlerts.tsx",
      "reason": "Re-export page, not directly routed",
      "action": "Remove, use component directly if needed"
    }
  ],
  "orphanComponents": [
    {
      "file": "frontend\\src\\components\\admin\\Communications.tsx",
      "reason": "Only used by unrouted Communications page",
      "action": "Remove or integrate"
    },
    {
      "file": "frontend\\src\\components\\admin\\CookApprovals.tsx",
      "reason": "Only used by unrouted CookApprovals page",
      "action": "Remove or integrate into user-management"
    },
    {
      "file": "frontend\\src\\components\\admin\\DeliveryAgentApprovals.tsx",
      "reason": "Only used by unrouted DeliveryAgentApprovals page",
      "action": "Remove or integrate into user-management"
    },
    {
      "file": "frontend\\src\\components\\admin\\Profile.tsx",
      "reason": "Only used by unrouted Profile page",
      "action": "Remove or integrate into settings"
    },
    {
      "file": "frontend\\src\\components\\admin\\Reports.tsx",
      "reason": "Only used by unrouted Reports page",
      "action": "Remove or integrate into system-analytics"
    },
    {
      "file": "frontend\\src\\components\\admin\\UnifiedApprovals.tsx",
      "reason": "Only used by unrouted UnifiedApprovals page",
      "action": "Remove or merge into user-management"
    },
    {
      "file": "frontend\\src\\components\\admin\\UserApproval.tsx",
      "reason": "Only used by unrouted UserApproval page",
      "action": "Remove or integrate into user-management"
    },
    {
      "file": "frontend\\src\\components\\admin\\communications\\ComplaintManagement.tsx",
      "reason": "Used by Complaints page (routed) and re-export page",
      "action": "Keep, used by routed page"
    },
    {
      "file": "frontend\\src\\components\\admin\\communications\\EmailTemplates.tsx",
      "reason": "Not used by any routed page",
      "action": "Remove or integrate into settings or notifications"
    },
    {
      "file": "frontend\\src\\components\\admin\\communications\\FeedbackManagement.tsx",
      "reason": "Used by Complaints page (routed)",
      "action": "Keep, used by routed page"
    },
    {
      "file": "frontend\\src\\components\\admin\\communications\\SystemAlerts.tsx",
      "reason": "Not used by any routed page",
      "action": "Remove or integrate into notifications or system-analytics"
    }
  ],
  "notes": "Only the 8 canonical admin pages are routed. All other admin pages and their components are orphans unless integrated into the canonical pages."
}